splicon/__init__.py
splicon/splicon.py
splicon-1.0.2.dist-info/METADATA
splicon-1.0.2.dist-info/WHEEL
splicon-1.0.2.dist-info/entry_points.txt
splicon-1.0.2.dist-info/top_level.txt
splicon-1.0.2.dist-info/RECORD
