Metadata-Version: 2.1
Name: splicon
Version: 1.0.2
Summary: Create Splunk icons for App/Add-On Development
Home-page: UNKNOWN
Author: Sebastian Schimper
Author-email: sebastianschimper@gmail.com
License: UNKNOWN
Keywords: python,splunk,icon,development
Platform: UNKNOWN
Classifier: Development Status :: 1 - Planning
Classifier: Intended Audience :: Developers
Classifier: Programming Language :: Python :: 3
Classifier: Operating System :: Unix
Classifier: Operating System :: MacOS :: MacOS X
Classifier: Operating System :: Microsoft :: Windows
Requires-Dist: argparse
Requires-Dist: pillow
